segfast/__init__.py
segfast/loader.py
segfast/memmap_loader.py
segfast/segyio_loader.py
segfast/trace_header_spec.py
segfast/utils.py
segfast-1.1.0.dist-info/licenses/LICENSE
segfast-1.1.0.dist-info/METADATA
segfast-1.1.0.dist-info/WHEEL
segfast-1.1.0.dist-info/top_level.txt
segfast-1.1.0.dist-info/RECORD
