Metadata-Version: 2.4
Name: segfast
Version: 1.1.0
Summary: A library for interacting with SEG-Y seismic data
Home-page: https://github.com/analysiscenter/segfast
Author: Sergey Tsimfer
Author-email: sergeytsimfer@gmail.com
License: Apache License 2.0
Platform: any
Classifier: License :: OSI Approved :: Apache Software License
Classifier: Operating System :: OS Independent
Classifier: Programming Language :: Python :: 3.8
Classifier: Programming Language :: Python :: 3.9
Classifier: Programming Language :: Python :: 3.10
License-File: LICENSE
Requires-Dist: dill>=0.3.1.1
Requires-Dist: numpy>=1.20.0
Requires-Dist: pandas>=1.0.0
Requires-Dist: numba>=0.54.0
Requires-Dist: segyio>=1.9.0
Dynamic: author
Dynamic: author-email
Dynamic: classifier
Dynamic: description
Dynamic: description-content-type
Dynamic: home-page
Dynamic: license
Dynamic: license-file
Dynamic: platform
Dynamic: requires-dist
Dynamic: summary
